punjabi_verbs/__init__.py
punjabi_verbs/verbs.py
punjabi_verbs-0.1.dist-info/METADATA
punjabi_verbs-0.1.dist-info/WHEEL
punjabi_verbs-0.1.dist-info/top_level.txt
punjabi_verbs-0.1.dist-info/RECORD
