Metadata-Version: 2.1
Name: punjabi_verbs
Version: 0.1
Summary: A package for Punjabi verbs
Home-page: https://github.com/MuhammadshoaibTahir/punjabiverbs.git
Author: Muhammad Shoaib Tahir
Author-email: shoaibtahir410@gmail.com
Classifier: Programming Language :: Python :: 3
Classifier: License :: OSI Approved :: MIT License
Classifier: Operating System :: OS Independent
Requires-Python: >=3.6
